<?xml version="1.0" encoding="UTF-8"?><!--Sample XML file generated by XMLSpy v2008 (http://www.altova.com)--><TWM_Manifest xsi:noNamespaceSchemaLocation="manifest.xsd" xmlns:xsi="http://www.w3.org/2001/XMLSchema-instance">

<Identification_segment>		
	<Registry_number/>		
	<Bol_reference/>		
	<Customs_office_segment>
		<Code/>		
	</Customs_office_segment>	
</Identification_segment>	

<Bol_specific_segment>		
	<Line_number/>		
	<Previous_document_reference/>		
	<Bol_Nature/>		
	<Unique_carrier_reference/>		
	<Total_number_of_containers/>		
	<Total_gross_mass_manifested/>		
	<Volume_in_cubic_meters/>		
	<Bol_type_segment>			
		<Code/>		
	</Bol_type_segment>		
	<Exporter_segment>			
		<Code/>			
		<Name oes1-unsign-content="true">
		</Name>			
		<Address oes1-unsign-content="true">
		</Address>		
	</Exporter_segment>
	<Consignee_segment>
		<Code/>			
		<Name oes1-unsign-content="true"> 
		</Name>			
		<Address oes1-unsign-content="true">
		</Address>		
	</Consignee_segment>		
	<Notify_segment>			
		<Code/>			
		<Name oes1-unsign-content="true">
		</Name>			
		<Address oes1-unsign-content="true">
		</Address>		
	</Notify_segment>		
	<Place_of_loading_segment>			
		<Code/>		
	</Place_of_loading_segment>		
	<Place_of_unloading_segment>			
		<Code/>		
	</Place_of_unloading_segment>		
	<Packages_segment>			
		<Package_type_code/>			
		<Number_of_packages/>		
	</Packages_segment>		
	<Shipping_segment>			
		<Shipping_marks/>		
	</Shipping_segment>		
	<Goods_segment>			
		<Goods_description/>		
	</Goods_segment>		
	<Freight_segment>			
		<Value/>			
		<Currency/>			
		<Indicator_segment>				
			<Code/>			
		</Indicator_segment>		
	</Freight_segment>		
	<Customs_segment>			
		<Value/>			
		<Currency/>		
	</Customs_segment>		
	<Transport_segment>			
		<Value/>			
		<Currency/>		
	</Transport_segment>		
	<Insurance_segment>			
		<Value/>			
		<Currency/>		
	</Insurance_segment>		
	<Seals_segment>			
		<Number_of_seals/>			
		<Marks_of_seals/>			
		<Sealing_party_code/>		
	</Seals_segment>		
	<Information_segment>			
		<Information_part_a/>		
	</Information_segment>		
	<Operations_segment>			
		<Location_segment>				
			<Code/>				
			<Information/>			
		</Location_segment>		
	</Operations_segment>	
</Bol_specific_segment>	
<Container>		
	<Reference/>		
	<Number/>		
	<Type/>		
	<Empty_full/>		
	<Seals/>		
	<Marks1/>		
	<Marks2/>		
	<Sealing_party/>	
</Container>	

</TWM_Manifest>	